[
  {
    "segment_id": 0,
    "start_seconds": 0.0,
    "end_seconds": 2.7,
    "start_time": "00:00",
    "end_time": "00:02",
    "segment_text": " بسم الله الرحمن الرحيم",
    "matched_ayah_text": "بِسْمِ ٱللَّهِ ٱلرَّحْمَـٰنِ ٱلرَّحِيمِ وَٱلشَّمْسِ وَضُحَىٰهَا",
    "matched_ayah_id": null,
    "score": 63.33333333333333
  },
  {
    "segment_id": 1,
    "start_seconds": 30.0,
    "end_seconds": 34.8,
    "start_time": "00:30",
    "end_time": "00:34",
    "segment_text": " مزكاها وقد خاب من ذساها",
    "matched_ayah_text": "وَقَدْ خَابَ مَن دَسَّىٰهَا",
    "matched_ayah_id": null,
    "score": 70.0
  },
  {
    "segment_id": 2,
    "start_seconds": 34.8,
    "end_seconds": 39.3,
    "start_time": "00:34",
    "end_time": "00:39",
    "segment_text": " كذبت ثمود بطغواها",
    "matched_ayah_text": "كَذَّبَتْ ثَمُودُ بِطَغْوَىٰهَآ",
    "matched_ayah_id": null,
    "score": 88.88888888888889
  },
  {
    "segment_id": 3,
    "start_seconds": 39.3,
    "end_seconds": 42.8,
    "start_time": "00:39",
    "end_time": "00:42",
    "segment_text": " إذن بعث أشقاها",
    "matched_ayah_text": "إِذِ ٱنۢبَعَثَ أَشْقَىٰهَا",
    "matched_ayah_id": null,
    "score": 77.41935483870968
  },
  {
    "segment_id": 4,
    "start_seconds": 42.8,
    "end_seconds": 45.6,
    "start_time": "00:42",
    "end_time": "00:45",
    "segment_text": " فقال لهم رسول الله",
    "matched_ayah_text": "فَقَالَ لَهُمْ رَسُولُ ٱللَّهِ نَاقَةَ ٱللَّهِ وَسُقْيَـٰهَا",
    "matched_ayah_id": null,
    "score": 66.66666666666667
  },
  {
    "segment_id": 5,
    "start_seconds": 45.6,
    "end_seconds": 49.2,
    "start_time": "00:45",
    "end_time": "00:49",
    "segment_text": " ناقة الله وسخياها",
    "matched_ayah_text": "فَقَالَ لَهُمْ رَسُولُ ٱللَّهِ نَاقَةَ ٱللَّهِ وَسُقْيَـٰهَا",
    "matched_ayah_id": null,
    "score": 52.83018867924528
  },
  {
    "segment_id": 6,
    "start_seconds": 49.2,
    "end_seconds": 52.0,
    "start_time": "00:49",
    "end_time": "00:52",
    "segment_text": " فكذبوه فعقروها",
    "matched_ayah_text": "كَذَّبَتْ ثَمُودُ بِطَغْوَىٰهَآ",
    "matched_ayah_id": null,
    "score": 48.484848484848484
  },
  {
    "segment_id": 7,
    "start_seconds": 52.0,
    "end_seconds": 55.2,
    "start_time": "00:52",
    "end_time": "00:55",
    "segment_text": " فدمدم عليهم ربهم",
    "matched_ayah_text": "فَكَذَّبُوهُ فَعَقَرُوهَا فَدَمْدَمَ عَلَيْهِمْ رَبُّهُم بِذَنۢبِهِمْ فَسَوَّىٰهَا",
    "matched_ayah_id": null,
    "score": 50.79365079365079
  },
  {
    "segment_id": 8,
    "start_seconds": 55.2,
    "end_seconds": 58.5,
    "start_time": "00:55",
    "end_time": "00:58",
    "segment_text": " بذنبهم فسواها",
    "matched_ayah_text": "وَنَفْسٍ وَمَا سَوَّىٰهَا",
    "matched_ayah_id": null,
    "score": 50.0
  },
  {
    "segment_id": 9,
    "start_seconds": 58.5,
    "end_seconds": 62.0,
    "start_time": "00:58",
    "end_time": "01:02",
    "segment_text": " ولا يخاف عقوباها",
    "matched_ayah_text": "وَلَا يَخَافُ عُقْبَـٰهَا",
    "matched_ayah_id": null,
    "score": 90.32258064516128
  }
]