[
    {
        "ayah": 22,
        "start_seconds": 104.66,
        "end_seconds": 114.66,
        "start_time": "01:44",
        "end_time": "01:54",
        "text": "وَمَا صَاحِبُكُم بِمَجْنُونٍ",
        "score": 0.5
    },
    {
        "ayah": 28,
        "start_seconds": 127.7,
        "end_seconds": 142.58,
        "start_time": "02:07",
        "end_time": "02:22",
        "text": "لِمَن شَآءَ مِنكُمْ أَن يَسْتَقِيمَ",
        "score": 0.56
    },
    {
        "ayah": 29,
        "start_seconds": 142.58,
        "end_seconds": 155.54,
        "start_time": "02:22",
        "end_time": "02:35",
        "text": "وَمَا تَشَآءُونَ إِلَّآ أَن يَشَآءَ ٱللَّهُ رَبُّ ٱلْعَـٰلَمِينَ",
        "score": 0.68
    }
]