[
    {
        "ayah": 1,
        "start_seconds": 9.8,
        "end_seconds": 16.0,
        "start_time": "00:09",
        "end_time": "00:16",
        "text": "بِسْمِ ٱللَّهِ ٱلرَّحْمَـٰنِ ٱلرَّحِيمِ أَلَمْ تَرَ كَيْفَ فَعَلَ رَبُّكَ بِأَصْحَـٰبِ ٱلْفِيلِ",
        "score": 0.46
    },
    {
        "ayah": 2,
        "start_seconds": 16.0,
        "end_seconds": 20.4,
        "start_time": "00:16",
        "end_time": "00:20",
        "text": "أَلَمْ يَجْعَلْ كَيْدَهُمْ فِى تَضْلِيلٍ",
        "score": 0.7
    },
    {
        "ayah": 3,
        "start_seconds": 20.4,
        "end_seconds": 24.64,
        "start_time": "00:20",
        "end_time": "00:24",
        "text": "وَأَرْسَلَ عَلَيْهِمْ طَيْرًا أَبَابِيلَ",
        "score": 0.66
    },
    {
        "ayah": 4,
        "start_seconds": 24.64,
        "end_seconds": 31.24,
        "start_time": "00:24",
        "end_time": "00:31",
        "text": "تَرْمِيهِم بِحِجَارَةٍ مِّن سِجِّيلٍ",
        "score": 0.72
    },
    {
        "ayah": 5,
        "start_seconds": 31.24,
        "end_seconds": 36.24,
        "start_time": "00:31",
        "end_time": "00:36",
        "text": "فَجَعَلَهُمْ كَعَصْفٍ مَّأْكُولٍۭ",
        "score": 0.6
    }
]