[
  {
    "segment_id": 0,
    "start_seconds": 0.0,
    "end_seconds": 6.72,
    "start_time": "00:00",
    "end_time": "00:06",
    "segment_text": " أعوذ بالله من الشيطان الرجيم بسم الله الرحمن الرحيم",
    "matched_ayah_text": "بِسْمِ ٱللَّهِ ٱلرَّحْمَـٰنِ ٱلرَّحِيمِ أَلْهَىٰكُمُ ٱلتَّكَاثُرُ",
    "matched_ayah_id": null,
    "score": 44.44444444444444
  },
  {
    "segment_id": 1,
    "start_seconds": 6.72,
    "end_seconds": 12.32,
    "start_time": "00:06",
    "end_time": "00:12",
    "segment_text": " ألهاكم التكاثر حتى زرتم المقابر",
    "matched_ayah_text": "حَتَّىٰ زُرْتُمُ ٱلْمَقَابِرَ",
    "matched_ayah_id": null,
    "score": 62.5
  },
  {
    "segment_id": 2,
    "start_seconds": 12.32,
    "end_seconds": 15.6,
    "start_time": "00:12",
    "end_time": "00:15",
    "segment_text": " كلا سوف تعلمون",
    "matched_ayah_text": "كَلَّا سَوْفَ تَعْلَمُونَ",
    "matched_ayah_id": null,
    "score": 100.0
  },
  {
    "segment_id": 3,
    "start_seconds": 15.6,
    "end_seconds": 19.6,
    "start_time": "00:15",
    "end_time": "00:19",
    "segment_text": " ثم كلا سوف تعلمون",
    "matched_ayah_text": "ثُمَّ كَلَّا سَوْفَ تَعْلَمُونَ",
    "matched_ayah_id": null,
    "score": 100.0
  },
  {
    "segment_id": 4,
    "start_seconds": 19.6,
    "end_seconds": 24.48,
    "start_time": "00:19",
    "end_time": "00:24",
    "segment_text": " كلا لو تعلمون علما اليقين",
    "matched_ayah_text": "كَلَّا لَوْ تَعْلَمُونَ عِلْمَ ٱلْيَقِينِ",
    "matched_ayah_id": null,
    "score": 93.87755102040816
  },
  {
    "segment_id": 5,
    "start_seconds": 24.48,
    "end_seconds": 27.84,
    "start_time": "00:24",
    "end_time": "00:27",
    "segment_text": " لترون الجحيم",
    "matched_ayah_text": "لَتَرَوُنَّ ٱلْجَحِيمَ",
    "matched_ayah_id": null,
    "score": 91.66666666666666
  },
  {
    "segment_id": 6,
    "start_seconds": 27.84,
    "end_seconds": 33.2,
    "start_time": "00:27",
    "end_time": "00:33",
    "segment_text": " ثم لترونها عين اليقين",
    "matched_ayah_text": "ثُمَّ لَتَرَوُنَّهَا عَيْنَ ٱلْيَقِينِ",
    "matched_ayah_id": null,
    "score": 95.23809523809523
  },
  {
    "segment_id": 7,
    "start_seconds": 33.2,
    "end_seconds": 40.24,
    "start_time": "00:33",
    "end_time": "00:40",
    "segment_text": " ثم لتسألون يومئذ عن النعيم",
    "matched_ayah_text": "ثُمَّ لَتُسْـَٔلُنَّ يَوْمَئِذٍ عَنِ ٱلنَّعِيمِ",
    "matched_ayah_id": null,
    "score": 90.19607843137256
  }
]