[
  {
    "segment_id": 0,
    "start_seconds": 0.0,
    "end_seconds": 4.2,
    "start_time": "00:00",
    "end_time": "00:04",
    "segment_text": " بسم الله الرحمن الرحيم",
    "matched_ayah_text": "بِسْمِ ٱللَّهِ ٱلرَّحْمَـٰنِ ٱلرَّحِيمِ وَٱلسَّمَآءِ ذَاتِ ٱلْبُرُوجِ",
    "matched_ayah_id": null,
    "score": 58.46153846153845
  },
  {
    "segment_id": 1,
    "start_seconds": 4.2,
    "end_seconds": 15.56,
    "start_time": "00:04",
    "end_time": "00:15",
    "segment_text": " والسماء ذات البروج واليوم الموعود وشاهد ومشهود",
    "matched_ayah_text": "وَشَاهِدٍ وَمَشْهُودٍ",
    "matched_ayah_id": null,
    "score": 41.379310344827594
  },
  {
    "segment_id": 2,
    "start_seconds": 15.56,
    "end_seconds": 24.400000000000002,
    "start_time": "00:15",
    "end_time": "00:24",
    "segment_text": " قتل أصحاب لخدود النار ذات الوقود إذ هم عليها قعود",
    "matched_ayah_text": "إِذْ هُمْ عَلَيْهَا قُعُودٌ",
    "matched_ayah_id": null,
    "score": 49.23076923076923
  },
  {
    "segment_id": 3,
    "start_seconds": 24.599999999999998,
    "end_seconds": 30.2,
    "start_time": "00:24",
    "end_time": "00:30",
    "segment_text": " وهم على ما يفعلون بالمومنين شهود",
    "matched_ayah_text": "وَهُمْ عَلَىٰ مَا يَفْعَلُونَ بِٱلْمُؤْمِنِينَ شُهُودٌ",
    "matched_ayah_id": null,
    "score": 92.3076923076923
  },
  {
    "segment_id": 4,
    "start_seconds": 30.2,
    "end_seconds": 44.08,
    "start_time": "00:30",
    "end_time": "00:44",
    "segment_text": " وما نقموا منهم إلا أن يؤمنوا بالله العزيز الحميد",
    "matched_ayah_text": "وَمَا نَقَمُوا۟ مِنْهُمْ إِلَّآ أَن يُؤْمِنُوا۟ بِٱللَّهِ ٱلْعَزِيزِ ٱلْحَمِيدِ",
    "matched_ayah_id": null,
    "score": 90.9090909090909
  },
  {
    "segment_id": 5,
    "start_seconds": 44.76,
    "end_seconds": 49.36,
    "start_time": "00:44",
    "end_time": "00:49",
    "segment_text": " الذي له ملك السماوات ولرض",
    "matched_ayah_text": "ٱلَّذِى لَهُۥ مُلْكُ ٱلسَّمَـٰوَٰتِ وَٱلْأَرْضِ ۚ وَٱللَّهُ عَلَىٰ كُلِّ شَىْءٍ شَهِيدٌ",
    "matched_ayah_id": null,
    "score": 53.84615384615385
  },
  {
    "segment_id": 6,
    "start_seconds": 49.36,
    "end_seconds": 55.76,
    "start_time": "00:49",
    "end_time": "00:55",
    "segment_text": " والله على كل شيء شهيد",
    "matched_ayah_text": "ٱلَّذِى لَهُۥ مُلْكُ ٱلسَّمَـٰوَٰتِ وَٱلْأَرْضِ ۚ وَٱللَّهُ عَلَىٰ كُلِّ شَىْءٍ شَهِيدٌ",
    "matched_ayah_id": null,
    "score": 56.75675675675676
  },
  {
    "segment_id": 7,
    "start_seconds": 55.76,
    "end_seconds": 63.8,
    "start_time": "00:55",
    "end_time": "01:03",
    "segment_text": " إن الذين فتنوا المومنين والمومنات ثم لم يتوبوا",
    "matched_ayah_text": "إِنَّ ٱلَّذِينَ فَتَنُوا۟ ٱلْمُؤْمِنِينَ وَٱلْمُؤْمِنَـٰتِ ثُمَّ لَمْ يَتُوبُوا۟ فَلَهُمْ عَذَابُ جَهَنَّمَ وَلَهُمْ عَذَابُ ٱلْحَرِيقِ",
    "matched_ayah_id": null,
    "score": 63.49206349206349
  },
  {
    "segment_id": 8,
    "start_seconds": 63.8,
    "end_seconds": 70.16,
    "start_time": "01:03",
    "end_time": "01:10",
    "segment_text": " فلهم عذاب جهنم ولهم عذاب الحريق",
    "matched_ayah_text": "إِنَّ ٱلَّذِينَ فَتَنُوا۟ ٱلْمُؤْمِنِينَ وَٱلْمُؤْمِنَـٰتِ ثُمَّ لَمْ يَتُوبُوا۟ فَلَهُمْ عَذَابُ جَهَنَّمَ وَلَهُمْ عَذَابُ ٱلْحَرِيقِ",
    "matched_ayah_id": null,
    "score": 54.054054054054056
  },
  {
    "segment_id": 9,
    "start_seconds": 70.24,
    "end_seconds": 81.64,
    "start_time": "01:10",
    "end_time": "01:21",
    "segment_text": " إن الذين آمنوا وعملوا الصالحات لهم جنات تجري من تحتها لنهار",
    "matched_ayah_text": "إِنَّ ٱلَّذِينَ ءَامَنُوا۟ وَعَمِلُوا۟ ٱلصَّـٰلِحَـٰتِ لَهُمْ جَنَّـٰتٌ تَجْرِى مِن تَحْتِهَا ٱلْأَنْهَـٰرُ ۚ ذَٰلِكَ ٱلْفَوْزُ ٱلْكَبِيرُ",
    "matched_ayah_id": null,
    "score": 74.12587412587412
  },
  {
    "segment_id": 10,
    "start_seconds": 81.64,
    "end_seconds": 85.08,
    "start_time": "01:21",
    "end_time": "01:25",
    "segment_text": " ذلك الفوز الكبير",
    "matched_ayah_text": "فَعَّالٌ لِّمَا يُرِيدُ",
    "matched_ayah_id": null,
    "score": 41.379310344827594
  },
  {
    "segment_id": 11,
    "start_seconds": 85.08,
    "end_seconds": 89.08,
    "start_time": "01:25",
    "end_time": "01:29",
    "segment_text": " إن بطش ربك لشديد",
    "matched_ayah_text": "إِنَّ بَطْشَ رَبِّكَ لَشَدِيدٌ",
    "matched_ayah_id": null,
    "score": 100.0
  },
  {
    "segment_id": 12,
    "start_seconds": 89.08,
    "end_seconds": 93.44,
    "start_time": "01:29",
    "end_time": "01:33",
    "segment_text": " إنه هو يبدئ ويعيد",
    "matched_ayah_text": "إِنَّهُۥ هُوَ يُبْدِئُ وَيُعِيدُ",
    "matched_ayah_id": null,
    "score": 97.14285714285714
  },
  {
    "segment_id": 13,
    "start_seconds": 93.44,
    "end_seconds": 96.84,
    "start_time": "01:33",
    "end_time": "01:36",
    "segment_text": " وهو الغفور الودود",
    "matched_ayah_text": "وَهُوَ ٱلْغَفُورُ ٱلْوَدُودُ",
    "matched_ayah_id": null,
    "score": 88.23529411764706
  },
  {
    "segment_id": 14,
    "start_seconds": 96.84,
    "end_seconds": 99.84,
    "start_time": "01:36",
    "end_time": "01:39",
    "segment_text": " ذو العرش المجيد",
    "matched_ayah_text": "ذُو ٱلْعَرْشِ ٱلْمَجِيدُ",
    "matched_ayah_id": null,
    "score": 86.66666666666667
  },
  {
    "segment_id": 15,
    "start_seconds": 100.52000000000001,
    "end_seconds": 103.52000000000001,
    "start_time": "01:40",
    "end_time": "01:43",
    "segment_text": " فعال لما يريد",
    "matched_ayah_text": "فَعَّالٌ لِّمَا يُرِيدُ",
    "matched_ayah_id": null,
    "score": 100.0
  },
  {
    "segment_id": 16,
    "start_seconds": 103.52000000000001,
    "end_seconds": 108.52000000000001,
    "start_time": "01:43",
    "end_time": "01:48",
    "segment_text": " هل تاك حديث الجنود فرعون وثمود",
    "matched_ayah_text": "هَلْ أَتَىٰكَ حَدِيثُ ٱلْجُنُودِ",
    "matched_ayah_id": null,
    "score": 64.0
  },
  {
    "segment_id": 17,
    "start_seconds": 108.52000000000001,
    "end_seconds": 120.52000000000001,
    "start_time": "01:48",
    "end_time": "02:00",
    "segment_text": " بل الذين كفروا في تكذيب والله من ورائهم محيط",
    "matched_ayah_text": "بَلِ ٱلَّذِينَ كَفَرُوا۟ فِى تَكْذِيبٍ",
    "matched_ayah_id": null,
    "score": 64.70588235294117
  },
  {
    "segment_id": 18,
    "start_seconds": 120.52000000000001,
    "end_seconds": 128.52,
    "start_time": "02:00",
    "end_time": "02:08",
    "segment_text": " بل هو قرآن مجيد في لوح محفوظ",
    "matched_ayah_text": "بَلْ هُوَ قُرْءَانٌ مَّجِيدٌ",
    "matched_ayah_id": null,
    "score": 68.18181818181819
  }
]