{
  "surah": 105,
  "ayahs": [
    {
      "ayah": 1,
      "text": "بِسْمِ ٱللَّهِ ٱلرَّحْمَـٰنِ ٱلرَّحِيمِ أَلَمْ تَرَ كَيْفَ فَعَلَ رَبُّكَ بِأَصْحَـٰبِ ٱلْفِيلِ",
      "start": 2.03,
      "end": 14.39,
      "matched_text": "بسم الله الرحمن الرحيم ألم تر كيف فعل ربك بأصحاب الفيل",
      "confidence": 1,
      "matched_word_indices": [
        0,
        10
      ]
    },
    {
      "ayah": 2,
      "text": "أَلَمْ يَجْعَلْ كَيْدَهُمْ فِى تَضْلِيلٍ",
      "start": 15.03,
      "end": 19.27,
      "matched_text": "ألم يجعل كيدهم في تضلي",
      "confidence": 1,
      "matched_word_indices": [
        11,
        15
      ]
    },
    {
      "ayah": 3,
      "text": "وَأَرْسَلَ عَلَيْهِمْ طَيْرًا أَبَابِيلَ",
      "start": 21.83,
      "end": 25.75,
      "matched_text": "وأرسل عليهم طيرا أباب",
      "confidence": 1,
      "matched_word_indices": [
        16,
        19
      ]
    },
    {
      "ayah": 4,
      "text": "تَرْمِيهِم بِحِجَارَةٍ مِّن سِجِّيلٍ",
      "start": 27.16,
      "end": 34.98,
      "matched_text": "ترميه بحجارة من سجي",
      "confidence": 1,
      "matched_word_indices": [
        20,
        23
      ]
    },
    {
      "ayah": 5,
      "text": "فَجَعَلَهُمْ كَعَصْفٍ مَّأْكُولٍۭ",
      "start": 36.74,
      "end": 41.12,
      "matched_text": "فجعلهم كعصف مأكوم",
      "confidence": 1,
      "matched_word_indices": [
        24,
        26
      ]
    }
  ],
  "alignment_score": 25.025
}